cal_rec_boxes/__init__.py
cal_rec_boxes/main.py
ch_ppocr_cls/__init__.py
ch_ppocr_cls/main.py
ch_ppocr_cls/utils.py
ch_ppocr_det/__init__.py
ch_ppocr_det/main.py
ch_ppocr_det/utils.py
ch_ppocr_rec/__init__.py
ch_ppocr_rec/main.py
ch_ppocr_rec/typings.py
ch_ppocr_rec/utils.py
inference_engine/__init__.py
inference_engine/base.py
inference_engine/openvino.py
inference_engine/paddle.py
inference_engine/torch.py
inference_engine/onnxruntime/__init__.py
inference_engine/onnxruntime/main.py
inference_engine/onnxruntime/provider_config.py
networks/__init__.py
networks/arch_config.yaml
networks/common.py
networks/architectures/__init__.py
networks/architectures/base_model.py
networks/backbones/__init__.py
networks/backbones/det_mobilenet_v3.py
networks/backbones/rec_hgnet.py
networks/backbones/rec_lcnetv3.py
networks/backbones/rec_mobilenet_v3.py
networks/backbones/rec_mv1_enhance.py
networks/backbones/rec_svtrnet.py
networks/heads/__init__.py
networks/heads/cls_head.py
networks/heads/det_db_head.py
networks/heads/rec_ctc_head.py
networks/heads/rec_multi_head.py
networks/necks/__init__.py
networks/necks/db_fpn.py
networks/necks/intracl.py
networks/necks/rnn.py
rapidocr_glock_fei-3.2.5.data/data/requirements.txt
utils/__init__.py
utils/download_file.py
utils/load_image.py
utils/logger.py
utils/output.py
utils/parse_parameters.py
utils/process_img.py
utils/to_markdown.py
utils/typings.py
utils/utils.py
utils/vis_res.py
rapidocr_glock_fei-3.2.5.dist-info/METADATA
rapidocr_glock_fei-3.2.5.dist-info/WHEEL
rapidocr_glock_fei-3.2.5.dist-info/entry_points.txt
rapidocr_glock_fei-3.2.5.dist-info/top_level.txt
rapidocr_glock_fei-3.2.5.dist-info/RECORD
